crayonai_stream/__init__.py
crayonai_stream/best_effort_json_parser.py
crayonai_stream/crayon_message.py
crayonai_stream/integrations/__init__.py
crayonai_stream/integrations/openai/__init__.py
crayonai_stream/integrations/openai/helper.py
crayonai_stream/integrations/openai/stream.py
crayonai_stream/js_schema_helpers.py
crayonai_stream/logger.py
crayonai_stream/protocol.py
crayonai_stream/py.typed
crayonai_stream/sse.py
crayonai_stream/stream.py
crayonai_stream-0.6.1.dist-info/METADATA
crayonai_stream-0.6.1.dist-info/WHEEL
crayonai_stream-0.6.1.dist-info/RECORD
