Metadata-Version: 2.1
Name: crayonai_stream
Version: 0.6.1
Summary: Streaming utilities for CrayonAI
License: MIT
Author: Thesys Inc.
Author-email: engineering@thesys.dev
Requires-Python: >=3.9
Classifier: License :: OSI Approved :: MIT License
Classifier: Programming Language :: Python :: 3
Classifier: Programming Language :: Python :: 3.9
Classifier: Programming Language :: Python :: 3.10
Classifier: Programming Language :: Python :: 3.11
Classifier: Programming Language :: Python :: 3.12
Requires-Dist: pydantic (>=2.0.0)
Requires-Dist: types-setuptools (>=76.0.0.20250313,<77.0.0.0)
Requires-Dist: typing-extensions (>=4.0.0)
